tomesd/__init__.py
tomesd/merge.py
tomesd/patch.py
tomesd/utils.py
tomesd-0.1.3.dist-info/LICENSE
tomesd-0.1.3.dist-info/METADATA
tomesd-0.1.3.dist-info/WHEEL
tomesd-0.1.3.dist-info/top_level.txt
tomesd-0.1.3.dist-info/RECORD
