Metadata-Version: 2.1
Name: tomesd
Version: 0.1.3
Summary: Token Merging for Stable Diffusion
Home-page: https://github.com/dbolya/tomesd
Author: Daniel Bolya
License: MIT
License-File: LICENSE
Requires-Dist: torch (>=1.12.1)
